uglyduck/.DS_Store
uglyduck/__init__.py
uglyduck/analyzer.py
uglyduck/inspector.py
uglyduck/parse.py
uglyduck/tests.py
uglyduck/types.py
uglyduck/utils.py
uglyduck-0.0.3.dist-info/METADATA
uglyduck-0.0.3.dist-info/WHEEL
uglyduck-0.0.3.dist-info/licenses/LICENSE
uglyduck-0.0.3.dist-info/RECORD
