Metadata-Version: 2.1
Name: uglyduck
Version: 0.0.3
Summary: Generate a types.py file for a package that contains protocols for classes generated from the files specified.
Project-URL: Homepage, https://github.com/malero/uglyduck
Project-URL: Bug Tracker, https://github.com/malero/uglyduck/issues
Author-email: Malero <contact@maleero.com>
License-File: LICENSE
Classifier: License :: OSI Approved :: MIT License
Classifier: Operating System :: OS Independent
Classifier: Programming Language :: Python :: 3.8
Requires-Python: >=3.8
